{
  "url": "https://thanhnien.vn/chi-dan-huu-tin-va-loat-sao-viet-gay-on-ao-vi-dinh-toi-ma-tuy-185241110141122628.htm",
  "title": "Chi Dân, Hữu Tín và loạt sao Việt gây ồn ào vì dính tới ma túy",
  "source_name": "Thanh Niên",
  "date_published": "2024-11-10",
  "date_crawled": "2026-06-08",
  "content_markdown": "# Chi Dân, Hữu Tín và loạt sao Việt gây ồn ào vì dính tới ma túy\n\nBài tổng hợp của Thanh Niên điểm lại nhiều trường hợp người nổi tiếng Việt Nam bị điều tra, khởi tố hoặc xét xử do liên quan đến ma túy. Nội dung đề cập đến ca sĩ Chi Dân, người mẫu Andrea Aybar/An Tây, diễn viên Hữu Tín, Lệ Hằng và một số nhân vật khác.\n\nNguồn tin cho biết ở thời điểm bài viết đăng, Công an quận Tân Bình đang phối hợp với các đơn vị liên quan điều tra vụ ca sĩ Chi Dân cùng một số người khác nghi liên quan đến ma túy. Bài cũng nhắc việc người mẫu An Tây bị đưa về trụ sở làm việc sau khi lực lượng chức năng kiểm tra một căn hộ và phát hiện nhóm người có dấu hiệu liên quan chất cấm.\n\nBài này hữu ích cho dataset vì đóng vai trò nguồn tổng hợp, giúp chatbot có bối cảnh rộng hơn về nhiều vụ việc. Tuy nhiên khi trả lời, hệ thống RAG nên ưu tiên nguồn chính thức hoặc bài chuyên biệt cho từng vụ nếu câu hỏi yêu cầu chi tiết pháp lý.",
  "content_type": "paraphrased_summary_for_rag",
  "copyright_note": "This JSON contains a paraphrased summary and metadata, not a full verbatim copy of the copyrighted article."
}